updownio_exporter.py
updownio_exporter-0.0.12.dist-info/METADATA
updownio_exporter-0.0.12.dist-info/WHEEL
updownio_exporter-0.0.12.dist-info/RECORD
