Metadata-Version: 2.3
Name: updownio-exporter
Version: 0.0.12
Summary: 
Requires-Python: >=3.13
Classifier: Development Status :: 5 - Production/Stable
Requires-Dist: daemon-metrics (==1.0.0)
Requires-Dist: prometheus-client (>=0.21.1)
Requires-Dist: requests (>=2.32.3)
Requires-Dist: the-conf (>=1.0.5)
